promptix/__init__.py
promptix/core/__init__.py
promptix/core/base.py
promptix/core/builder.py
promptix/core/config.py
promptix/core/container.py
promptix/core/exceptions.py
promptix/core/validation.py
promptix/core/workspace_manager.py
promptix/core/adapters/__init__.py
promptix/core/adapters/_base.py
promptix/core/adapters/anthropic.py
promptix/core/adapters/openai.py
promptix/core/components/__init__.py
promptix/core/components/model_config_builder.py
promptix/core/components/prompt_loader.py
promptix/core/components/template_renderer.py
promptix/core/components/variable_validator.py
promptix/core/components/version_manager.py
promptix/core/storage/__init__.py
promptix/core/storage/loaders.py
promptix/core/storage/manager.py
promptix/core/storage/utils.py
promptix/enhancements/__init__.py
promptix/enhancements/logging.py
promptix/tools/cli.py
promptix/tools/hook_manager.py
promptix/tools/version_manager.py
promptix/tools/studio/__init__.py
promptix/tools/studio/app.py
promptix/tools/studio/data.py
promptix/tools/studio/folder_manager.py
promptix/tools/studio/logo.ico
promptix/tools/studio/logo.webp
promptix/tools/studio/pages/dashboard.py
promptix/tools/studio/pages/library.py
promptix/tools/studio/pages/playground.py
promptix/tools/studio/pages/version.py
promptix-0.2.0.dist-info/licenses/LICENSE
promptix-0.2.0.dist-info/METADATA
promptix-0.2.0.dist-info/WHEEL
promptix-0.2.0.dist-info/entry_points.txt
promptix-0.2.0.dist-info/top_level.txt
promptix-0.2.0.dist-info/RECORD
