Metadata-Version: 2.4
Name: promptix
Version: 0.2.0
Summary: Professional prompt management with Git-native version control, dynamic templating, and visual Studio UI for production LLM applications
Author-email: Promptix Contributors <contact@promptix.io>
License: MIT
Keywords: prompt,management,llm,ai,studio,templates
Classifier: Development Status :: 4 - Beta
Classifier: Intended Audience :: Developers
Classifier: Programming Language :: Python :: 3
Classifier: Programming Language :: Python :: 3.9
Classifier: Programming Language :: Python :: 3.10
Classifier: Programming Language :: Python :: 3.11
Classifier: License :: OSI Approved :: MIT License
Classifier: Operating System :: OS Independent
Classifier: Topic :: Software Development :: Libraries :: Python Modules
Classifier: Topic :: Text Processing :: General
Requires-Python: >=3.9
License-File: LICENSE
Requires-Dist: streamlit>=1.29.0
Requires-Dist: jinja2>=3.0.0
Requires-Dist: python-dotenv>=0.19.0
Requires-Dist: pyyaml>=6.0.0
Requires-Dist: jsonschema>=4.0.0
Requires-Dist: rich>=13.0.0
Requires-Dist: click>=8.0.0
Provides-Extra: dev
Requires-Dist: pytest>=7.0.0; extra == "dev"
Requires-Dist: pytest-cov>=4.0.0; extra == "dev"
Requires-Dist: pytest-mock>=3.10.0; extra == "dev"
Requires-Dist: pytest-watch>=4.2.0; extra == "dev"
Requires-Dist: build>=1.0.0; extra == "dev"
Requires-Dist: twine>=4.0.0; extra == "dev"
Requires-Dist: black>=23.0.0; extra == "dev"
Requires-Dist: isort>=5.0.0; extra == "dev"
Requires-Dist: flake8>=6.0.0; extra == "dev"
Requires-Dist: flake8-docstrings>=1.7.0; extra == "dev"
Requires-Dist: flake8-bugbear>=23.0.0; extra == "dev"
Requires-Dist: flake8-comprehensions>=3.14.0; extra == "dev"
Requires-Dist: flake8-implicit-str-concat>=0.4.0; extra == "dev"
Requires-Dist: flake8-simplify>=0.20.0; extra == "dev"
Requires-Dist: mypy>=1.0.0; extra == "dev"
Requires-Dist: types-PyYAML>=6.0.0; extra == "dev"
Requires-Dist: types-requests>=2.0.0; extra == "dev"
Requires-Dist: pydocstyle>=6.3.0; extra == "dev"
Requires-Dist: bandit>=1.7.5; extra == "dev"
Requires-Dist: safety>=2.3.0; extra == "dev"
Requires-Dist: pip-audit>=2.6.0; extra == "dev"
Requires-Dist: sphinx>=7.0.0; extra == "dev"
Requires-Dist: sphinx-rtd-theme>=1.3.0; extra == "dev"
Requires-Dist: sphinx-autodoc-typehints>=1.24.0; extra == "dev"
Requires-Dist: myst-parser>=2.0.0; extra == "dev"
Requires-Dist: radon>=6.0.0; extra == "dev"
Requires-Dist: xenon>=0.9.0; extra == "dev"
Requires-Dist: vulture>=2.9.0; extra == "dev"
Requires-Dist: interrogate>=1.5.0; extra == "dev"
Requires-Dist: pre-commit>=3.0.0; extra == "dev"
Requires-Dist: pip-tools>=7.0.0; extra == "dev"
Requires-Dist: pipdeptree>=2.13.0; extra == "dev"
Requires-Dist: memory-profiler>=0.61.0; extra == "dev"
Requires-Dist: ipython>=8.0.0; extra == "dev"
Requires-Dist: rich>=13.0.0; extra == "dev"
Requires-Dist: click>=8.0.0; extra == "dev"
Provides-Extra: docs
Requires-Dist: sphinx>=7.0.0; extra == "docs"
Requires-Dist: sphinx-rtd-theme>=1.3.0; extra == "docs"
Requires-Dist: sphinx-autodoc-typehints>=1.24.0; extra == "docs"
Requires-Dist: myst-parser>=2.0.0; extra == "docs"
Provides-Extra: security
Requires-Dist: bandit>=1.7.5; extra == "security"
Requires-Dist: safety>=2.3.0; extra == "security"
Requires-Dist: pip-audit>=2.6.0; extra == "security"
Dynamic: license-file
